README.md
prettymatrix.py
setup.py
prettymatrix.egg-info/PKG-INFO
prettymatrix.egg-info/SOURCES.txt
prettymatrix.egg-info/dependency_links.txt
prettymatrix.egg-info/requires.txt
prettymatrix.egg-info/top_level.txt