Metadata-Version: 1.0
Name: prettymatrix
Version: 1.0.0
Summary: Pretty printer for matrices and column vectors.
Home-page: https://github.com/samueljamesbell/prettymatrix
Author: Samuel Bell
Author-email: samueljamesbell@gmail.com
License: MIT
Keywords: matrix matrices vector formatting string numpy
Platform: UNKNOWN
